galaxy/__init__.py
galaxy/py.typed
galaxy/objectstore/__init__.py
galaxy/objectstore/_caching_base.py
galaxy/objectstore/_util.py
galaxy/objectstore/azure_blob.py
galaxy/objectstore/badges.py
galaxy/objectstore/caching.py
galaxy/objectstore/cloud.py
galaxy/objectstore/irods.py
galaxy/objectstore/onedata.py
galaxy/objectstore/pithos.py
galaxy/objectstore/pulsar.py
galaxy/objectstore/rucio.py
galaxy/objectstore/rucio_extra_clients.py
galaxy/objectstore/s3.py
galaxy/objectstore/s3_boto3.py
galaxy/objectstore/s3_multipart_upload.py
galaxy/objectstore/examples/__init__.py
galaxy/objectstore/templates/__init__.py
galaxy/objectstore/templates/manager.py
galaxy/objectstore/templates/models.py
galaxy/objectstore/templates/examples/__init__.py
galaxy/objectstore/templates/examples/azure_just_container.yml
galaxy/objectstore/templates/examples/cloudflare.yml
galaxy/objectstore/templates/examples/cloudflare_legacy.yml
galaxy/objectstore/templates/examples/irods.yml
galaxy/objectstore/templates/examples/irods_ssl.yml
galaxy/objectstore/templates/examples/minio_example.yml
galaxy/objectstore/templates/examples/minio_just_buckets.yml
galaxy/objectstore/templates/examples/minio_just_buckets_legacy.yml
galaxy/objectstore/templates/examples/onedata.yml
galaxy/objectstore/templates/examples/production_aws_s3.yml
galaxy/objectstore/templates/examples/production_aws_s3_legacy.yml
galaxy/objectstore/templates/examples/production_azure_blob.yml
galaxy/objectstore/templates/examples/production_gcp_s3.yml
galaxy/objectstore/templates/examples/production_generic_s3.yml
galaxy/objectstore/templates/examples/production_generic_s3_legacy.yml
galaxy/objectstore/templates/examples/rucio.yml
galaxy/objectstore/templates/examples/simple_example.yml
galaxy/objectstore/templates/examples/testing_multi_version_with_secrets.yml
galaxy/objectstore/unittest_utils/__init__.py
galaxy_objectstore-25.0.3.dist-info/licenses/LICENSE
galaxy_objectstore-25.0.3.dist-info/METADATA
galaxy_objectstore-25.0.3.dist-info/WHEEL
galaxy_objectstore-25.0.3.dist-info/top_level.txt
galaxy_objectstore-25.0.3.dist-info/RECORD
